pygohcl.cpython-311-darwin.h
pygohcl.cpython-311-darwin.so
pygohcl-1.2.5.dist-info/RECORD
pygohcl-1.2.5.dist-info/WHEEL
pygohcl-1.2.5.dist-info/top_level.txt
pygohcl-1.2.5.dist-info/METADATA
pygohcl/__init__.py
pygohcl/build_cffi.py
pygohcl/_pygohcl.py
